protogen/__init__.py
protogen/_case.py
protogen/py.typed
protogen/test.py
protogen-0.3.1.dist-info/METADATA
protogen-0.3.1.dist-info/WHEEL
protogen-0.3.1.dist-info/RECORD
