Metadata-Version: 2.1
Name: protogen
Version: 0.3.1
Summary: protogen makes writing protoc plugins easy.
Home-page: https://github.com/fischor/protogen-python
License: MIT
Keywords: proto,protoc,Protobuf,Protocol buffers,Code generation
Author: fischor
Author-email: fischor.sh@gmail.com
Maintainer: fischor
Maintainer-email: fischor.sh@gmail.com
Requires-Python: >=3.7,<4.0
Classifier: License :: OSI Approved :: MIT License
Classifier: Programming Language :: Python :: 3
Classifier: Programming Language :: Python :: 3.7
Classifier: Programming Language :: Python :: 3.8
Classifier: Programming Language :: Python :: 3.9
Classifier: Programming Language :: Python :: 3.10
Classifier: Programming Language :: Python :: 3.11
Requires-Dist: protobuf (>=3.20.3)
Project-URL: Repository, https://github.com/fischor/protogen-python
